alloniaconfigs/__init__.py
alloniaconfigs/configs.py
alloniaconfigs-1.1.2.dist-info/METADATA
alloniaconfigs-1.1.2.dist-info/WHEEL
alloniaconfigs-1.1.2.dist-info/RECORD
