Metadata-Version: 2.1
Name: alloniaconfigs
Version: 1.1.2
Summary: Class to handle configurations
Author: ALEIA
Requires-Python: >=3.9,<4.0
Classifier: Programming Language :: Python :: 3
Classifier: Programming Language :: Python :: 3.9
Classifier: Programming Language :: Python :: 3.10
Classifier: Programming Language :: Python :: 3.11
Classifier: Programming Language :: Python :: 3.12
Requires-Dist: pydantic (>=2.7.0,<3.0.0)
Requires-Dist: python-dotenv (>=1.0.1,<2.0.0)
